CHANGES.txt
LICENSE.txt
MANIFEST.in
README.rst
setup.cfg
setup.py
TkLsystem.egg-info/PKG-INFO
TkLsystem.egg-info/SOURCES.txt
TkLsystem.egg-info/dependency_links.txt
TkLsystem.egg-info/entry_points.txt
TkLsystem.egg-info/top_level.txt
lsystem/__init__.py
lsystem/__main__.py
lsystem/canvas_pil.py
lsystem/canvas_tk.py
lsystem/l_system_utils.py
lsystem/lsturtle.py
lsystem/examples/8bit.lsf
lsystem/examples/bug.lsf
lsystem/examples/custom_tree.lsf
lsystem/examples/custom_tree2.lsf
lsystem/examples/custom_tree3.lsf
lsystem/examples/dragon_curve.lsf
lsystem/examples/fibotree.lsf
lsystem/examples/fractal_plant.lsf
lsystem/examples/joined_cross_curves.lsf
lsystem/examples/kevs-wispy.lsf
lsystem/examples/kevs.lsf
lsystem/examples/kevs_pond.lsf
lsystem/examples/koch_curve.lsf
lsystem/examples/koch_snowflake.lsf
lsystem/examples/lace.lsf
lsystem/examples/ormanlik-daglar.lsf
lsystem/examples/pleasant_error.lsf
lsystem/examples/sierpinski-carpet(gaps).lsf
lsystem/examples/sierpinski-median-curve.lsf
lsystem/examples/sierpinski.lsf
lsystem/examples/sierpinski2.lsf
lsystem/examples/sierpinski_carpet.lsf
lsystem/examples/space_filling.lsf
lsystem/examples/spiral.lsf