Metadata-Version: 1.1
Name: TkLsystem
Version: 0.2.1
Summary: 
